gns_pytorch/__init__.py
gns_pytorch/gns.py
gns_pytorch-0.1.5.dist-info/METADATA
gns_pytorch-0.1.5.dist-info/WHEEL
gns_pytorch-0.1.5.dist-info/entry_points.txt
gns_pytorch-0.1.5.dist-info/RECORD
