Metadata-Version: 2.4
Name: gns-pytorch
Version: 0.1.5
Summary: Simple Gradient Noise Scale (GNS) calculation for PyTorch
Author-email: elyx <elio@pascarelli.com>
Requires-Python: >=3.9
Requires-Dist: numpy>=2.0.0
Requires-Dist: torch>=2.0.0
